tencentcloud/__init__.py
tencentcloud/advisor/__init__.py
tencentcloud/advisor/v20200721/__init__.py
tencentcloud/advisor/v20200721/advisor_client.py
tencentcloud/advisor/v20200721/advisor_client_async.py
tencentcloud/advisor/v20200721/errorcodes.py
tencentcloud/advisor/v20200721/models.py
tencentcloud/ai3d/__init__.py
tencentcloud/ai3d/v20250513/__init__.py
tencentcloud/ai3d/v20250513/ai3d_client.py
tencentcloud/ai3d/v20250513/ai3d_client_async.py
tencentcloud/ai3d/v20250513/errorcodes.py
tencentcloud/ai3d/v20250513/models.py
tencentcloud/aiart/__init__.py
tencentcloud/aiart/v20221229/__init__.py
tencentcloud/aiart/v20221229/aiart_client.py
tencentcloud/aiart/v20221229/aiart_client_async.py
tencentcloud/aiart/v20221229/errorcodes.py
tencentcloud/aiart/v20221229/models.py
tencentcloud/ams/__init__.py
tencentcloud/ams/v20201229/__init__.py
tencentcloud/ams/v20201229/ams_client.py
tencentcloud/ams/v20201229/ams_client_async.py
tencentcloud/ams/v20201229/errorcodes.py
tencentcloud/ams/v20201229/models.py
tencentcloud/antiddos/__init__.py
tencentcloud/antiddos/v20200309/__init__.py
tencentcloud/antiddos/v20200309/antiddos_client.py
tencentcloud/antiddos/v20200309/antiddos_client_async.py
tencentcloud/antiddos/v20200309/errorcodes.py
tencentcloud/antiddos/v20200309/models.py
tencentcloud/apigateway/__init__.py
tencentcloud/apigateway/v20180808/__init__.py
tencentcloud/apigateway/v20180808/apigateway_client.py
tencentcloud/apigateway/v20180808/apigateway_client_async.py
tencentcloud/apigateway/v20180808/errorcodes.py
tencentcloud/apigateway/v20180808/models.py
tencentcloud/apm/__init__.py
tencentcloud/apm/v20210622/__init__.py
tencentcloud/apm/v20210622/apm_client.py
tencentcloud/apm/v20210622/apm_client_async.py
tencentcloud/apm/v20210622/errorcodes.py
tencentcloud/apm/v20210622/models.py
tencentcloud/asr/__init__.py
tencentcloud/asr/v20190614/__init__.py
tencentcloud/asr/v20190614/asr_client.py
tencentcloud/asr/v20190614/asr_client_async.py
tencentcloud_sdk_python_intl_en-3.1.41.dist-info/METADATA
tencentcloud_sdk_python_intl_en-3.1.41.dist-info/WHEEL
tencentcloud_sdk_python_intl_en-3.1.41.dist-info/top_level.txt
tencentcloud_sdk_python_intl_en-3.1.41.dist-info/RECORD
